kedroio/__init__.py
kedroio/connectors/__init__.py
kedroio/connectors/aws/__init__.py
kedroio/connectors/aws/_base.py
kedroio/connectors/aws/athena.py
kedroio/connectors/aws/exceptions.py
kedroio/connectors/aws/s3.py
kedroio/connectors/util/__init__.py
kedroio/connectors/util/exceptions.py
kedroio/connectors/util/local.py
kedroio/connectors/util/progress.py
kedroio/datasets/__init__.py
kedroio/datasets/aws/__init__.py
kedroio/datasets/aws/athena.py
kedroio-0.1.3.dist-info/LICENSE.txt
kedroio-0.1.3.dist-info/WHEEL
kedroio-0.1.3.dist-info/METADATA
kedroio-0.1.3.dist-info/RECORD
