Metadata-Version: 2.1
Name: kedroio
Version: 0.1.3
Summary: Extension for `kedro` datasets
Home-page: https://github.com/atsangarides/kedroio
License: MIT
Keywords: data pipelines,kedro
Author: atsangarides
Author-email: andreas_tsangarides@hotmail.com
Requires-Python: >=3.8,<4.0
Classifier: Development Status :: 3 - Alpha
Classifier: Intended Audience :: Developers
Classifier: License :: OSI Approved :: MIT License
Classifier: Operating System :: OS Independent
Classifier: Programming Language :: Python :: 3
Classifier: Programming Language :: Python :: 3.10
Classifier: Programming Language :: Python :: 3.8
Classifier: Programming Language :: Python :: 3.9
Classifier: Topic :: Software Development :: Libraries :: Python Modules
Requires-Dist: boto3 (>=1.20.17,<2.0.0)
Requires-Dist: boto3-stubs[s3] (>=1.20.24,<2.0.0)
Requires-Dist: tqdm (>=4.62.3,<5.0.0)
Project-URL: Repository, https://github.com/atsangarides/kedroio
